streamlit_shadcn_component/__init__.py
streamlit_shadcn_component/component.py
streamlit_shadcn_component/frontend/dist/index.html
streamlit_shadcn_component/frontend/dist/vite.svg
streamlit_shadcn_component/frontend/dist/assets/index-YXkX9oYg.css
streamlit_shadcn_component/frontend/dist/assets/index-pZNrLHlX.js
my_custom_streamlit_component_shadcn-0.0.8.dist-info/METADATA
my_custom_streamlit_component_shadcn-0.0.8.dist-info/WHEEL
my_custom_streamlit_component_shadcn-0.0.8.dist-info/top_level.txt
my_custom_streamlit_component_shadcn-0.0.8.dist-info/RECORD
