Metadata-Version: 2.4
Name: my-custom-streamlit-component-shadcn
Version: 0.0.8
Summary: This is my first custom component in streamlit with help of recat and shadcn
Home-page: 
Author: Saurabh
Author-email: saurabhk4789@gmail.com
Requires-Python: >=3.7
Requires-Dist: streamlit>=0.63
Provides-Extra: devel
Requires-Dist: wheel; extra == "devel"
Requires-Dist: pytest==7.4.0; extra == "devel"
Requires-Dist: playwright==1.48.0; extra == "devel"
Requires-Dist: requests==2.31.0; extra == "devel"
Requires-Dist: pytest-playwright-snapshot==1.0; extra == "devel"
Requires-Dist: pytest-rerunfailures==12.0; extra == "devel"
Dynamic: author
Dynamic: author-email
Dynamic: description-content-type
Dynamic: provides-extra
Dynamic: requires-dist
Dynamic: requires-python
Dynamic: summary
